invenio_queues/__init__.py
invenio_queues/cli.py
invenio_queues/config.py
invenio_queues/errors.py
invenio_queues/ext.py
invenio_queues/proxies.py
invenio_queues/queue.py
invenio_queues/utils.py
invenio_queues-1.0.2.dist-info/licenses/AUTHORS.rst
invenio_queues-1.0.2.dist-info/licenses/LICENSE
invenio_queues-1.0.2.dist-info/METADATA
invenio_queues-1.0.2.dist-info/WHEEL
invenio_queues-1.0.2.dist-info/entry_points.txt
invenio_queues-1.0.2.dist-info/top_level.txt
invenio_queues-1.0.2.dist-info/RECORD
