Metadata-Version: 2.4
Name: invenio-queues
Version: 1.0.2
Summary: "Invenio module for managing queues."
Home-page: https://github.com/inveniosoftware/invenio-queues
Author: CERN
Author-email: info@inveniosoftware.org
License: MIT
Keywords: invenio TODO
Platform: any
Classifier: Development Status :: 5 - Production/Stable
Requires-Python: >=3.6
License-File: LICENSE
License-File: AUTHORS.rst
Requires-Dist: invenio-base<3.0.0,>=2.2.0
Requires-Dist: invenio-celery<3.0.0,>=2.2.0
Requires-Dist: redis>=3.4.0
Provides-Extra: tests
Requires-Dist: pytest-black>=0.3.10; extra == "tests"
Requires-Dist: pytest-invenio<3.0.0,>=2.1.0; extra == "tests"
Requires-Dist: Sphinx>=4.5.0; extra == "tests"
Provides-Extra: docs
Dynamic: license-file
